ecephys_spike_sorting/__init__.py
ecephys_spike_sorting/common/OEFileInfo.py
ecephys_spike_sorting/common/__init__.py
ecephys_spike_sorting/common/epoch.py
ecephys_spike_sorting/common/schemas.py
ecephys_spike_sorting/common/utils.py
ecephys_spike_sorting/common/visualization.py
ecephys_spike_sorting/modules/__init__.py
ecephys_spike_sorting/modules/automerging/__init__.py
ecephys_spike_sorting/modules/automerging/__main__.py
ecephys_spike_sorting/modules/automerging/_schemas.py
ecephys_spike_sorting/modules/automerging/automerging.py
ecephys_spike_sorting/modules/automerging/merges.py
ecephys_spike_sorting/modules/automerging/metrics.py
ecephys_spike_sorting/modules/automerging/spike_ISI.py
ecephys_spike_sorting/modules/depth_estimation/__init__.py
ecephys_spike_sorting/modules/depth_estimation/__main__.py
ecephys_spike_sorting/modules/depth_estimation/_schemas.py
ecephys_spike_sorting/modules/depth_estimation/depth_estimation.py
ecephys_spike_sorting/modules/extract_from_npx/__init__.py
ecephys_spike_sorting/modules/extract_from_npx/__main__.py
ecephys_spike_sorting/modules/extract_from_npx/_schemas.py
ecephys_spike_sorting/modules/extract_from_npx/create_settings_json.py
ecephys_spike_sorting/modules/kilosort_helper/__init__.py
ecephys_spike_sorting/modules/kilosort_helper/__main__.py
ecephys_spike_sorting/modules/kilosort_helper/_schemas.py
ecephys_spike_sorting/modules/kilosort_helper/matlab_file_generator.py
ecephys_spike_sorting/modules/kilosort_postprocessing/__init__.py
ecephys_spike_sorting/modules/kilosort_postprocessing/__main__.py
ecephys_spike_sorting/modules/kilosort_postprocessing/_schemas.py
ecephys_spike_sorting/modules/kilosort_postprocessing/postprocessing.py
ecephys_spike_sorting/modules/mean_waveforms/__init__.py
ecephys_spike_sorting/modules/mean_waveforms/__main__.py
ecephys_spike_sorting/modules/mean_waveforms/_schemas.py
ecephys_spike_sorting/modules/mean_waveforms/extract_waveforms.py
forked_ecephys_spike_sorting-0.1.1.dist-info/AUTHORS.rst
forked_ecephys_spike_sorting-0.1.1.dist-info/LICENSE.txt
forked_ecephys_spike_sorting-0.1.1.dist-info/METADATA
forked_ecephys_spike_sorting-0.1.1.dist-info/WHEEL
forked_ecephys_spike_sorting-0.1.1.dist-info/entry_points.txt
forked_ecephys_spike_sorting-0.1.1.dist-info/top_level.txt
forked_ecephys_spike_sorting-0.1.1.dist-info/RECORD
